HISTORY.rst
LICENSE.rst
README.rst
setup.py
src/collective/__init__.py
src/collective.js.angular.egg-info/PKG-INFO
src/collective.js.angular.egg-info/SOURCES.txt
src/collective.js.angular.egg-info/dependency_links.txt
src/collective.js.angular.egg-info/entry_points.txt
src/collective.js.angular.egg-info/namespace_packages.txt
src/collective.js.angular.egg-info/requires.txt
src/collective.js.angular.egg-info/top_level.txt
src/collective.js.angular.egg-info/zip-safe
src/collective/js/__init__.py
src/collective/js/angular/__init__.py
src/collective/js/angular/configure.zcml
src/collective/js/angular/example.pt
src/collective/js/angular/profiles/p4/cdn/jsregistry.xml
src/collective/js/angular/profiles/p4/cdn/metadata.xml
src/collective/js/angular/profiles/p4/minified/jsregistry.xml
src/collective/js/angular/profiles/p4/minified/metadata.xml
src/collective/js/angular/profiles/p4/uncompressed/jsregistry.xml
src/collective/js/angular/profiles/p4/uncompressed/metadata.xml
src/collective/js/angular/profiles/p5/default/metadata.xml
src/collective/js/angular/profiles/p5/default/registry.xml
src/collective/js/angular/resources/angular-animate.js
src/collective/js/angular/resources/angular-animate.min.js
src/collective/js/angular/resources/angular-animate.min.js.map
src/collective/js/angular/resources/angular-aria.js
src/collective/js/angular/resources/angular-aria.min.js
src/collective/js/angular/resources/angular-aria.min.js.map
src/collective/js/angular/resources/angular-cookies.js
src/collective/js/angular/resources/angular-cookies.min.js
src/collective/js/angular/resources/angular-cookies.min.js.map
src/collective/js/angular/resources/angular-csp.css
src/collective/js/angular/resources/angular-loader.js
src/collective/js/angular/resources/angular-loader.min.js
src/collective/js/angular/resources/angular-loader.min.js.map
src/collective/js/angular/resources/angular-messages.js
src/collective/js/angular/resources/angular-messages.min.js
src/collective/js/angular/resources/angular-messages.min.js.map
src/collective/js/angular/resources/angular-mocks.js
src/collective/js/angular/resources/angular-resource.js
src/collective/js/angular/resources/angular-resource.min.js
src/collective/js/angular/resources/angular-resource.min.js.map
src/collective/js/angular/resources/angular-route.js
src/collective/js/angular/resources/angular-route.min.js
